umbral/__about__.py
umbral/__init__.py
umbral/capsule.py
umbral/capsule_frag.py
umbral/curve.py
umbral/curve_point.py
umbral/curve_scalar.py
umbral/dem.py
umbral/errors.py
umbral/hashing.py
umbral/key_frag.py
umbral/keys.py
umbral/openssl.py
umbral/params.py
umbral/pre.py
umbral/serializable.py
umbral/signing.py
umbral-0.3.0.dist-info/LICENSE.md
umbral-0.3.0.dist-info/METADATA
umbral-0.3.0.dist-info/WHEEL
umbral-0.3.0.dist-info/top_level.txt
umbral-0.3.0.dist-info/RECORD
