Metadata-Version: 2.1
Name: umbral
Version: 0.3.0
Summary: NuCypher's Umbral Proxy Re-Encryption Implementation
Home-page: https://github.com/nucypher/pyUmbral
Author: NuCypher
Author-email: dev@nucypher.com
License: UNKNOWN
Platform: UNKNOWN
Classifier: Development Status :: 2 - Pre-Alpha
Classifier: Intended Audience :: Science/Research
Classifier: License :: OSI Approved :: GNU General Public License v3 (GPLv3)
Classifier: Natural Language :: English
Classifier: Programming Language :: Python :: Implementation
Classifier: Programming Language :: Python :: 3 :: Only
Classifier: Programming Language :: Python :: 3.6
Classifier: Programming Language :: Python :: 3.7
Classifier: Topic :: Scientific/Engineering
Requires-Python: >=3
Provides-Extra: testing
Provides-Extra: docs
Provides-Extra: benchmarks
License-File: LICENSE.md
